djrq_wrapper/__init__.py
djrq_wrapper/decorators.py
djrq_wrapper/wrappers.py
djrq_wrapper-0.0.1.dist-info/WHEEL
djrq_wrapper-0.0.1.dist-info/METADATA
djrq_wrapper-0.0.1.dist-info/RECORD
