Metadata-Version: 2.4
Name: djrq-wrapper
Version: 0.0.1
Summary: A simple wrapper arround django-rq
Author: Sydney Gems
Author-email: Sydney Gems <sydney@disroot.org>
License-Expression: GPL-3.0-or-later
Classifier: Programming Language :: Python :: 3
Classifier: Operating System :: OS Independent
Requires-Dist: build>=1.3.0
Requires-Dist: django-rq>=3.2.1
Requires-Python: >=3.9
Project-URL: Homepage, https://gitlab.com/daufinsyd/djrq-wrapper
Project-URL: Issues, https://gitlab.com/daufinsyd/djrq-wrapper/issues
